hdim_opt/__init__.py
hdim_opt/hyperellipsoid_sampling.py
hdim_opt/quasar_helpers.py
hdim_opt/quasar_optimization.py
hdim_opt/sobol_sampling.py
hdim_opt/sobol_sensitivity.py
hdim_opt/test_functions.py
hdim_opt/waveform_analysis.py
hdim_opt-1.3.0.dist-info/METADATA
hdim_opt-1.3.0.dist-info/WHEEL
hdim_opt-1.3.0.dist-info/top_level.txt
hdim_opt-1.3.0.dist-info/RECORD
