Metadata-Version: 2.4
Name: hdim_opt
Version: 1.3.0
Summary: Optimization toolkit for high-dimensional, non-differentiable problems.
Author-email: Julian Soltes <jsoltes@regis.edu>
License: MIT
Project-URL: Repository, https://github.com/jgsoltes/hdim_opt
Keywords: optimization,high-dimensional,sampling,QUASAR,hyperellipsoid
Classifier: Programming Language :: Python :: 3
Classifier: License :: OSI Approved :: MIT License
Classifier: Operating System :: OS Independent
Classifier: Intended Audience :: Science/Research
Classifier: Intended Audience :: Developers
Classifier: Topic :: Scientific/Engineering :: Mathematics
Classifier: Topic :: Scientific/Engineering :: Physics
Classifier: Topic :: Scientific/Engineering :: Artificial Intelligence
Requires-Python: >=3.8
Requires-Dist: numpy
Requires-Dist: scipy
Provides-Extra: hds
Requires-Dist: pandas; extra == "hds"
Requires-Dist: scikit-learn; extra == "hds"
Requires-Dist: joblib; extra == "hds"
Provides-Extra: sensitivity
Requires-Dist: pandas; extra == "sensitivity"
Requires-Dist: SALib; extra == "sensitivity"
